dynamicwf/__init__.py
dynamicwf/__main__.py
dynamicwf/server.py
dynamicwf-2025.1.0.dist-info/METADATA
dynamicwf-2025.1.0.dist-info/WHEEL
dynamicwf-2025.1.0.dist-info/entry_points.txt
dynamicwf-2025.1.0.dist-info/licenses/LICENSE
dynamicwf-2025.1.0.dist-info/RECORD
