Metadata-Version: 2.4
Name: dynamicwf
Version: 2025.1.0
Summary: A Model Context Protocol server providing tools to access Adobe Intern information
Author-email: Abhijeet Ahluwalia <abhijeeta@adobe.com>
License: MIT
License-File: LICENSE
Keywords: automation,interns,llm,mcp
Classifier: Development Status :: 4 - Beta
Classifier: Intended Audience :: Developers
Classifier: License :: OSI Approved :: MIT License
Classifier: Programming Language :: Python :: 3
Classifier: Programming Language :: Python :: 3.10
Requires-Python: >=3.10
Requires-Dist: click>=8.1.7
Requires-Dist: mcp>=1.0.0
Requires-Dist: pydantic>=2.0.0
